leanframe/__init__.py
leanframe/version.py
leanframe-0.1.0.dist-info/licenses/LICENSE
leanframe-0.1.0.dist-info/METADATA
leanframe-0.1.0.dist-info/WHEEL
leanframe-0.1.0.dist-info/top_level.txt
leanframe-0.1.0.dist-info/RECORD
