Metadata-Version: 2.4
Name: leanframe
Version: 0.1.0
Summary: LeanFrame is a pandas-like API built on top of Ibis.
Requires-Python: >=3.10
License-File: LICENSE
Requires-Dist: pandas>=2.2.0
Requires-Dist: pyarrow>=15.0.2
Requires-Dist: ibis-framework<11.0.0,>=10.3.1
Dynamic: license-file
